gcp_secret_manager_cli/__init__.py
gcp_secret_manager_cli/__main__.py
gcp_secret_manager_cli/cli.py
gcp_secret_manager_cli/core/__init__.py
gcp_secret_manager_cli/core/client.py
gcp_secret_manager_cli/core/manager.py
gcp_secret_manager_cli/utils/__init__.py
gcp_secret_manager_cli/utils/console.py
gcp_secret_manager_cli/utils/env.py
gcp_secret_manager_cli-0.0.6.dist-info/METADATA
gcp_secret_manager_cli-0.0.6.dist-info/WHEEL
gcp_secret_manager_cli-0.0.6.dist-info/entry_points.txt
gcp_secret_manager_cli-0.0.6.dist-info/licenses/LICENSE
gcp_secret_manager_cli-0.0.6.dist-info/RECORD
